LICENCE
README.md
setup.py
restaurante_sabor_express.egg-info/PKG-INFO
restaurante_sabor_express.egg-info/SOURCES.txt
restaurante_sabor_express.egg-info/dependency_links.txt
restaurante_sabor_express.egg-info/top_level.txt
sabor_express/__init__.py
sabor_express/sabor_express.py